utilipy/__init__.py
utilipy/_astropy_init.py
utilipy/conftest.py
utilipy/version.py
utilipy/data_utils/__init__.py
utilipy/data_utils/crossmatch.py
utilipy/data_utils/decorators.py
utilipy/data_utils/select.py
utilipy/data_utils/setup_package.py
utilipy/data_utils/utils.py
utilipy/data_utils/fitting/__init__.py
utilipy/data_utils/fitting/lmfit_utils.py
utilipy/data_utils/fitting/tests/__init__.py
utilipy/data_utils/fitting/tests/test_lmfit_utils.py
utilipy/data_utils/tests/__init__.py
utilipy/data_utils/tests/test_decorators.py
utilipy/data_utils/tests/test_init.py
utilipy/data_utils/tests/test_init_subpackages.py
utilipy/data_utils/tests/test_select.py
utilipy/data_utils/tests/test_utils.py
utilipy/data_utils/xfm/__init__.py
utilipy/data_utils/xfm/graph.py
utilipy/data_utils/xfm/transformations.py
utilipy/decorators/__init__.py
utilipy/decorators/baseclass.py
utilipy/decorators/code_dev.py
utilipy/decorators/docstring.py
utilipy/decorators/func_io.py
utilipy/decorators/setup_package.py
utilipy/decorators/tests/__init__.py
utilipy/decorators/tests/_null_imports.py
utilipy/decorators/tests/test_code_dev.py
utilipy/decorators/tests/test_docstring.py
utilipy/decorators/tests/test_dtype_decorator.py
utilipy/decorators/tests/test_func_io.py
utilipy/extern/__init__.py
utilipy/extern/doc_parse_tools/__init__.py
utilipy/extern/doc_parse_tools/_style_store.py
utilipy/extern/doc_parse_tools/napoleon_parse_tools.py
utilipy/extern/doc_parse_tools/numpy_parse_tools.py
utilipy/extern/doc_parse_tools/rest_parse_tools.py
utilipy/extern/doc_parse_tools/tests/__init__.py
utilipy/extern/doc_parse_tools/tests/test_napolean_parse_tools.py
utilipy/extern/doc_parse_tools/tests/test_numpy_parse_tools.py
utilipy/extern/doc_parse_tools/tests/test_rest_parse_tools.py
utilipy/extern/doc_parse_tools/tests/test_style_store.py
utilipy/imports/__init__.py
utilipy/imports/amuse_imports.py
utilipy/imports/astronat_imports.py
utilipy/imports/astropy_imports.py
utilipy/imports/base_imports.py
utilipy-1.1b1.dist-info/LICENSE.rst
utilipy-1.1b1.dist-info/METADATA
utilipy-1.1b1.dist-info/WHEEL
utilipy-1.1b1.dist-info/top_level.txt
utilipy-1.1b1.dist-info/RECORD
