Metadata-Version: 2.1
Name: utilipy
Version: 1.1b1
Summary: Python grab-bag.
Home-page: https://utilipy.readthedocs.io
Author: Nathaniel Starkman
Author-email: n.starkman@mail.utoronto.ca
License: BSD 3-Clause
Platform: UNKNOWN
Requires-Python: >=3.6
Requires-Dist: astropy
Requires-Dist: ipython
Requires-Dist: matplotlib
Requires-Dist: numpy
Requires-Dist: pandas
Requires-Dist: plotly
Requires-Dist: pytest (<6.0)
Requires-Dist: PyYAML
Requires-Dist: scipy
Requires-Dist: tqdm
Requires-Dist: typing-extensions
Requires-Dist: wrapt
Provides-Extra: all
Requires-Dist: scipy ; extra == 'all'
Requires-Dist: lmfit ; extra == 'all'
Requires-Dist: dill ; extra == 'all'
Provides-Extra: docs
Requires-Dist: sphinx-astropy ; extra == 'docs'
Requires-Dist: nbsphinx ; extra == 'docs'
Requires-Dist: jupyter-client ; extra == 'docs'
Requires-Dist: sphinxcontrib-bibtex (<2.0.0) ; extra == 'docs'
Provides-Extra: test
Requires-Dist: pytest-astropy ; extra == 'test'
Requires-Dist: pytest-astropy-header ; extra == 'test'
